<?xml version = '1.0' encoding = 'UTF-8'?>
<FKIndexAssociation class="oracle.dbtools.crest.model.design.relational.FKIndexAssociation" directorySegmentName="seg_0" id="3E5F5FC1-AA7B-6F09-2D65-CF3069EE3E07" containerWithKeyObject="20162D1C-3B7D-9EDE-2FD3-F5D53AE98E37" localFKIndex="227DA2EE-1719-07EA-00EC-D36D88900AA3" name="shipdate_ship_prop_FK">
<createdBy>ITPS</createdBy>
<createdTime>2024-04-29 05:45:54 UTC</createdTime>
<ownerDesignName>예제 물리 모델링</ownerDesignName>
<referredTableLongName>ship_prop</referredTableLongName>
<deleteRule>NO ACTION</deleteRule>
<referredTableID>8A85816B-1F76-6468-5585-80C9F483F431</referredTableID>
<keyObject>CB641A2F-B5A0-77FE-AF82-593E71A05F65</keyObject>
<referredKeyID>CB641A2F-B5A0-77FE-AF82-593E71A05F65</referredKeyID>
<mandatory>true</mandatory>
<refColNames>shipname</refColNames>
<transferable>true</transferable>
<rely>false</rely>
<columnDependencyConstraintGenerateInDDL>true</columnDependencyConstraintGenerateInDDL>
</FKIndexAssociation>